[{"author_id": 1487328266239184897, "id": 1495251678626717698, "text": "RT @CryptoRonnin: \ud83c\udf81 HYPE ALIENS GIVEAWAY \ud83c\udf81\n\n\ud83d\udea8 1 NFT + 10 WL SPOTS \ud83d\udc7d\n\nHow to enter:\n\u2705 Follow @HYPEALIENS\n\u2705 Like &amp; RT this tweet\n\u2705 Tag 1 frie\u2026"}, {"author_id": 1414569224857661440, "id": 1495251667901628419, "text": "My man saw the Aliens building the great pyramid of giza https://t.co/kr29aiSG48"}, {"author_id": 394216985, "id": 1495251628391288832, "text": "Nerf has outdone themselves with this Alines Pulse Blaster. \nhttps://t.co/GtzPF6lK9t"}, {"author_id": 1475745538632945665, "id": 1495251623139950597, "text": "RT @CryptoRonnin: \ud83c\udf81 HYPE ALIENS GIVEAWAY \ud83c\udf81\n\n\ud83d\udea8 1 NFT + 10 WL SPOTS \ud83d\udc7d\n\nHow to enter:\n\u2705 Follow @HYPEALIENS\n\u2705 Like &amp; RT this tweet\n\u2705 Tag 1 frie\u2026"}, {"author_id": 1393589851006529536, "id": 1495251569692246017, "text": "RT @CryptoRonnin: \ud83c\udf81 HYPE ALIENS GIVEAWAY \ud83c\udf81\n\n\ud83d\udea8 1 NFT + 10 WL SPOTS \ud83d\udc7d\n\nHow to enter:\n\u2705 Follow @HYPEALIENS\n\u2705 Like &amp; RT this tweet\n\u2705 Tag 1 frie\u2026"}, {"author_id": 541624787, "id": 1495251553682341889, "text": "RT @BuyNDips: I now own 3 super rare Nekkid Pluto aliens \ud83d\ude0e This is the key piece to the upcoming @nftworldsNFT Nekkid Paradise build. @Plut\u2026"}, {"author_id": 1422854035841814532, "id": 1495251513601449986, "text": "RT @CryptoRonnin: \ud83c\udf81 HYPE ALIENS GIVEAWAY \ud83c\udf81\n\n\ud83d\udea8 1 NFT + 10 WL SPOTS \ud83d\udc7d\n\nHow to enter:\n\u2705 Follow @HYPEALIENS\n\u2705 Like &amp; RT this tweet\n\u2705 Tag 1 frie\u2026"}, {"author_id": 1317415401094062080, "id": 1495251478382104578, "text": "RT @pcisbs1: Memo to Senior Democrats Shows that the Biden Admin will illegally continue to import as many unvetted, unvaccinated illegal a\u2026"}, {"author_id": 829772691955601408, "id": 1495251469716672514, "text": "RT @WendyHailey: OMG!!  Who did this\u2026 I just googled \u2018aliens\u2019 (watching Travel Channel)\u2026 and LOOK who showed UP!!  \ud83d\ude02 https://t.co/kRGgCestZN"}, {"author_id": 1476862373113831447, "id": 1495251461311279104, "text": "look at these cute aliens @ailenenemes #NFTdrop #NFTCollector https://t.co/GZ6KDuBdfi"}, {"author_id": 65140749, "id": 1495251419883917314, "text": "RT @goodblackdude: Wow, Canada looks insane! Whoa, Russia-Ukraine is heating up! Meanwhile, our own stateside southern border is being over\u2026"}, {"author_id": 1493828092116168705, "id": 1495251395619930114, "text": "RT @CryptoRonnin: \ud83c\udf81 HYPE ALIENS GIVEAWAY \ud83c\udf81\n\n\ud83d\udea8 1 NFT + 10 WL SPOTS \ud83d\udc7d\n\nHow to enter:\n\u2705 Follow @HYPEALIENS\n\u2705 Like &amp; RT this tweet\n\u2705 Tag 1 frie\u2026"}, {"author_id": 1461539491731095553, "id": 1495251395024461826, "text": "Do you believe in aliens?"}, {"author_id": 1459008383453839361, "id": 1495251314498220034, "text": "RT @CryptoRonnin: \ud83c\udf81 HYPE ALIENS GIVEAWAY \ud83c\udf81\n\n\ud83d\udea8 1 NFT + 10 WL SPOTS \ud83d\udc7d\n\nHow to enter:\n\u2705 Follow @HYPEALIENS\n\u2705 Like &amp; RT this tweet\n\u2705 Tag 1 frie\u2026"}, {"author_id": 1487364986687033346, "id": 1495251313554178050, "text": "RT @CryptoRonnin: \ud83c\udf81 HYPE ALIENS GIVEAWAY \ud83c\udf81\n\n\ud83d\udea8 1 NFT + 10 WL SPOTS \ud83d\udc7d\n\nHow to enter:\n\u2705 Follow @HYPEALIENS\n\u2705 Like &amp; RT this tweet\n\u2705 Tag 1 frie\u2026"}, {"author_id": 1476789908853301249, "id": 1495251227843649542, "text": "mint some before they run out of aliens @alienenemes #NFTartist #NFTCommunity https://t.co/wsNPYsT12H"}, {"author_id": 1489757067611348993, "id": 1495251218138300418, "text": "RT @CryptoRonnin: \ud83c\udf81 HYPE ALIENS GIVEAWAY \ud83c\udf81\n\n\ud83d\udea8 1 NFT + 10 WL SPOTS \ud83d\udc7d\n\nHow to enter:\n\u2705 Follow @HYPEALIENS\n\u2705 Like &amp; RT this tweet\n\u2705 Tag 1 frie\u2026"}, {"author_id": 1492788317904990211, "id": 1495251217886625795, "text": "RT @CryptoRonnin: \ud83c\udf81 HYPE ALIENS GIVEAWAY \ud83c\udf81\n\n\ud83d\udea8 1 NFT + 10 WL SPOTS \ud83d\udc7d\n\nHow to enter:\n\u2705 Follow @HYPEALIENS\n\u2705 Like &amp; RT this tweet\n\u2705 Tag 1 frie\u2026"}, {"author_id": 1368338265733005314, "id": 1495251193047756800, "text": "RT @_Knock_U_out_: Hey Tony That Shit ain`t so Great.\nhttps://t.co/K3A5QAauH5"}, {"author_id": 1482956062320107529, "id": 1495251191911292930, "text": "RT @CryptoRonnin: \ud83c\udf81 HYPE ALIENS GIVEAWAY \ud83c\udf81\n\n\ud83d\udea8 1 NFT + 10 WL SPOTS \ud83d\udc7d\n\nHow to enter:\n\u2705 Follow @HYPEALIENS\n\u2705 Like &amp; RT this tweet\n\u2705 Tag 1 frie\u2026"}, {"author_id": 1393520326919655424, "id": 1495251183363309569, "text": "RT @CryptoRonnin: \ud83c\udf81 HYPE ALIENS GIVEAWAY \ud83c\udf81\n\n\ud83d\udea8 1 NFT + 10 WL SPOTS \ud83d\udc7d\n\nHow to enter:\n\u2705 Follow @HYPEALIENS\n\u2705 Like &amp; RT this tweet\n\u2705 Tag 1 frie\u2026"}, {"author_id": 803704409523748864, "id": 1495251133392031747, "text": "RT @WendyHailey: OMG!!  Who did this\u2026 I just googled \u2018aliens\u2019 (watching Travel Channel)\u2026 and LOOK who showed UP!!  \ud83d\ude02 https://t.co/kRGgCestZN"}, {"author_id": 257170398, "id": 1495251123069980672, "text": "If there\u2019s other planets in the universe aren\u2019t we technically aliens too?"}, {"author_id": 1300740494629117952, "id": 1495251122306830342, "text": "RT @CryptoRonnin: \ud83c\udf81 HYPE ALIENS GIVEAWAY \ud83c\udf81\n\n\ud83d\udea8 1 NFT + 10 WL SPOTS \ud83d\udc7d\n\nHow to enter:\n\u2705 Follow @HYPEALIENS\n\u2705 Like &amp; RT this tweet\n\u2705 Tag 1 frie\u2026"}, {"author_id": 1473370165458972681, "id": 1495251118712143875, "text": "NFTs #nftart cute aliens about to pop. grab them @alienenemes https://t.co/JC9l2FQeNd"}, {"author_id": 1365488315479126021, "id": 1495251054144884738, "text": "RT @CryptoRonnin: \ud83c\udf81 HYPE ALIENS GIVEAWAY \ud83c\udf81\n\n\ud83d\udea8 1 NFT + 10 WL SPOTS \ud83d\udc7d\n\nHow to enter:\n\u2705 Follow @HYPEALIENS\n\u2705 Like &amp; RT this tweet\n\u2705 Tag 1 frie\u2026"}, {"author_id": 1486585515784937474, "id": 1495251042035924994, "text": "@luxuryse I believe i would be the last Wishing to all aliens out of the universe"}, {"author_id": 2515480024, "id": 1495251041029349378, "text": "RT @P8R1OT_PARADOX: We let them ruin our healthcare and are watching them give our country away to illegal aliens while they destroy our ki\u2026"}, {"author_id": 1303728983981338625, "id": 1495251032879816707, "text": "I talk about aliens and shit https://t.co/imTG3QAoAI"}, {"author_id": 1433659481414533125, "id": 1495251022637600772, "text": "RT @CryptoRonnin: \ud83c\udf81 HYPE ALIENS GIVEAWAY \ud83c\udf81\n\n\ud83d\udea8 1 NFT + 10 WL SPOTS \ud83d\udc7d\n\nHow to enter:\n\u2705 Follow @HYPEALIENS\n\u2705 Like &amp; RT this tweet\n\u2705 Tag 1 frie\u2026"}, {"author_id": 3064146644, "id": 1495250963984232450, "text": "RT @MainChannel_: '5\u2b50\ufe0f...elements of thrilling mystery, suspense, dystopian fantasy and science fiction.'\n\nThe Lenders Saga from @Travis_Bo\u2026"}, {"author_id": 1301829110256156678, "id": 1495250961605935105, "text": "RT @CryptoRonnin: \ud83c\udf81 HYPE ALIENS GIVEAWAY \ud83c\udf81\n\n\ud83d\udea8 1 NFT + 10 WL SPOTS \ud83d\udc7d\n\nHow to enter:\n\u2705 Follow @HYPEALIENS\n\u2705 Like &amp; RT this tweet\n\u2705 Tag 1 frie\u2026"}, {"author_id": 45128175, "id": 1495250959873806343, "text": "RT @ElieNYC: But the descendants of these whites would ban Derek Bell\u2019s Space Traders\u2014which is a short story about whites selling us to ali\u2026"}, {"author_id": 1414595989776838660, "id": 1495250950180716544, "text": "RT @CryptoRonnin: \ud83c\udf81 HYPE ALIENS GIVEAWAY \ud83c\udf81\n\n\ud83d\udea8 1 NFT + 10 WL SPOTS \ud83d\udc7d\n\nHow to enter:\n\u2705 Follow @HYPEALIENS\n\u2705 Like &amp; RT this tweet\n\u2705 Tag 1 frie\u2026"}, {"author_id": 746660067777273856, "id": 1495250943172034564, "text": "@gladstein thank you for this and for saving our planets from aliens https://t.co/4UbT29eZCv"}, {"author_id": 1527988244, "id": 1495250942295527425, "text": "RT @MainChannel_: '5\u2b50\ufe0f...elements of thrilling mystery, suspense, dystopian fantasy and science fiction.'\n\nThe Lenders Saga from @Travis_Bo\u2026"}, {"author_id": 1320937583744962560, "id": 1495250930140266496, "text": "@qnboo_ partying w the aliens rn"}, {"author_id": 1305385721591746566, "id": 1495250917960028164, "text": "Once we were called the spirit of the mountain. Father sun, mother moon. Ancestral spirits, animal spirits. Jinn. Ghosts. The green man. Then gods, demons. Angels. Poltergeists. Aliens, extraterrestrials. Leptons, quarks. The words change. We do not change."}, {"author_id": 932333637097332736, "id": 1495250868429475842, "text": "@RonFilipkowski wow!! the grifting never ends,hopefully in the rewrite of our Constitution &amp; Bill of Rights, the ability to make appeals for public support will require more substantial evidence than, \"Someone found a tracks of a green slime suggesting that aliens or the Black Lagoon creature.."}, {"author_id": 1436503925662920706, "id": 1495250858849804289, "text": "RT @BreitbartNews: As working class Americans struggle to remain afloat and afford groceries and gas in the disastrous Biden economy, Biden\u2026"}, {"author_id": 1398294879948656646, "id": 1495250818483765248, "text": "@seanragan @olegGD @Reuters 1/My scientific conclusion after having lived on 5 continents and having worked in politics, finance and economics: we r aliens who were sent from another planet to make life miserable for everything on this rock including ourselves. We r insane. We r hypocrites."}, {"author_id": 1481391630531764225, "id": 1495250813446283267, "text": "i hate small talk. bitch do u believe in aliens n do u think tupac still alive"}, {"author_id": 1473593054837854219, "id": 1495250802415390721, "text": "mint some before they run out of aliens @alienenemes #NFTdrop #NFTGiveaway https://t.co/qErkfpMD1F"}, {"author_id": 1471370225224462343, "id": 1495250796476346372, "text": "TRUMP PATRIOTS MARINES \n\nMOTHER FUCKERS \nTELL YOUR ALIENS\n\nNO STUPID  WITH ME\n\nMACHINE DONT LIKE STUPID https://t.co/DYS8RpwBqm"}, {"author_id": 23960704, "id": 1495250776637452288, "text": "RT @WendyHailey: OMG!!  Who did this\u2026 I just googled \u2018aliens\u2019 (watching Travel Channel)\u2026 and LOOK who showed UP!!  \ud83d\ude02 https://t.co/kRGgCestZN"}, {"author_id": 1473472326113001472, "id": 1495250771713327108, "text": "RT @CryptoRonnin: \ud83c\udf81 HYPE ALIENS GIVEAWAY \ud83c\udf81\n\n\ud83d\udea8 1 NFT + 10 WL SPOTS \ud83d\udc7d\n\nHow to enter:\n\u2705 Follow @HYPEALIENS\n\u2705 Like &amp; RT this tweet\n\u2705 Tag 1 frie\u2026"}, {"author_id": 1495212999443120128, "id": 1495250763152760836, "text": "RT @CryptoRonnin: \ud83c\udf81 HYPE ALIENS GIVEAWAY \ud83c\udf81\n\n\ud83d\udea8 1 NFT + 10 WL SPOTS \ud83d\udc7d\n\nHow to enter:\n\u2705 Follow @HYPEALIENS\n\u2705 Like &amp; RT this tweet\n\u2705 Tag 1 frie\u2026"}, {"author_id": 1002364881041936384, "id": 1495250690796515334, "text": "RT @BreitbartNews: As working class Americans struggle to remain afloat and afford groceries and gas in the disastrous Biden economy, Biden\u2026"}, {"author_id": 21989428, "id": 1495250679547367425, "text": "RT @WendyHailey: OMG!!  Who did this\u2026 I just googled \u2018aliens\u2019 (watching Travel Channel)\u2026 and LOOK who showed UP!!  \ud83d\ude02 https://t.co/kRGgCestZN"}, {"author_id": 1476223500335468550, "id": 1495250634274078720, "text": "I like 45 year old illegal aliens making my burrito at Chipotle.\nOur American teenagers don't need jobs anyway."}, {"author_id": 1478217328705761281, "id": 1495250610601730051, "text": "RT @CryptoRonnin: \ud83c\udf81 HYPE ALIENS GIVEAWAY \ud83c\udf81\n\n\ud83d\udea8 1 NFT + 10 WL SPOTS \ud83d\udc7d\n\nHow to enter:\n\u2705 Follow @HYPEALIENS\n\u2705 Like &amp; RT this tweet\n\u2705 Tag 1 frie\u2026"}, {"author_id": 2272035415, "id": 1495250610307874821, "text": "They come from distant stars and worlds beyond our own. Strange, dangerous, fascinating - dare you face the aliens? Dare you learn their secrets?\nHere Be Aliens!\nhttps://t.co/ZbvODnnn1n #Scifi #IARTG #ASMSG #TheAuthorGang"}, {"author_id": 3207673037, "id": 1495250594663223296, "text": "RT @NinjasyArt: How do aliens organize a party? They planet.\ud83d\udc7d\ud83d\ude02\nAlien Invader .018 ETH 100/1,000 minted on OpenSea.\n-\n  #NFT #NFTCommunity\u2026"}, {"author_id": 1466631927582969857, "id": 1495250584949166080, "text": "RT @CryptoRonnin: \ud83c\udf81 HYPE ALIENS GIVEAWAY \ud83c\udf81\n\n\ud83d\udea8 1 NFT + 10 WL SPOTS \ud83d\udc7d\n\nHow to enter:\n\u2705 Follow @HYPEALIENS\n\u2705 Like &amp; RT this tweet\n\u2705 Tag 1 frie\u2026"}, {"author_id": 32735766, "id": 1495250562035904512, "text": "UFO Crash, Castle, Egyptian Face Found On Sandwich Islands, UFO Sighting News. 100% proof of ancient aliens https://t.co/aphNo7u4oi #ancientaliens #googleearth \ud83d\udef8\ud83c\udff0\ud83d\udc7d"}, {"author_id": 1297835894758670337, "id": 1495250508126330885, "text": "RT @Queen_ofVirgo: not Beyonce, the aliens love her"}, {"author_id": 3510546680, "id": 1495250502287708160, "text": "@imcorinnemec @ItsToad_ @GaelicKat It\u2019s like the Cold for the aliens in \u2018War of the Worlds.\u2019"}, {"author_id": 387859027, "id": 1495250496357076992, "text": "@crani_boy I feel like a good conversation starter is: \n\n\u201cDo you believe in aliens?\u201d\n\nI feel like her answer to this would tell you if she definitely ISN\u2019T the one. Lol"}, {"author_id": 1494484571332964352, "id": 1495250495132565508, "text": "RT @CryptoRonnin: \ud83c\udf81 HYPE ALIENS GIVEAWAY \ud83c\udf81\n\n\ud83d\udea8 1 NFT + 10 WL SPOTS \ud83d\udc7d\n\nHow to enter:\n\u2705 Follow @HYPEALIENS\n\u2705 Like &amp; RT this tweet\n\u2705 Tag 1 frie\u2026"}, {"author_id": 1308750375634132995, "id": 1495250481509068800, "text": "RT @CryptoRonnin: \ud83c\udf81 HYPE ALIENS GIVEAWAY \ud83c\udf81\n\n\ud83d\udea8 1 NFT + 10 WL SPOTS \ud83d\udc7d\n\nHow to enter:\n\u2705 Follow @HYPEALIENS\n\u2705 Like &amp; RT this tweet\n\u2705 Tag 1 frie\u2026"}, {"author_id": 240451540, "id": 1495250471782543363, "text": "RT @JennyBurnley1: \"Aliens, secret portals, wormholes ... a brilliant, twist-filled #scifi.\" \nhttps://t.co/TmDD1eM48S  \n#Kindle #ebook #fan\u2026"}, {"author_id": 147121824, "id": 1495250451515994113, "text": "RT @CryptoRonnin: \ud83c\udf81 HYPE ALIENS GIVEAWAY \ud83c\udf81\n\n\ud83d\udea8 1 NFT + 10 WL SPOTS \ud83d\udc7d\n\nHow to enter:\n\u2705 Follow @HYPEALIENS\n\u2705 Like &amp; RT this tweet\n\u2705 Tag 1 frie\u2026"}, {"author_id": 174987132, "id": 1495250430514720768, "text": "RT @SteveHofstetter: When faced with a choice between accepting responsibility for something they've done or blaming anyone but themselves,\u2026"}, {"author_id": 3025920089, "id": 1495250397673541632, "text": "RT @fMRI_guy: Why do some people insist that ancient people were assisted by aliens when this idol clearly indicates that they were actuall\u2026"}, {"author_id": 2604005624, "id": 1495250378774003715, "text": "RT @BreitbartNews: As working class Americans struggle to remain afloat and afford groceries and gas in the disastrous Biden economy, Biden\u2026"}, {"author_id": 358563458, "id": 1495250370250952710, "text": "RT @CryptoRonnin: \ud83c\udf81 HYPE ALIENS GIVEAWAY \ud83c\udf81\n\n\ud83d\udea8 1 NFT + 10 WL SPOTS \ud83d\udc7d\n\nHow to enter:\n\u2705 Follow @HYPEALIENS\n\u2705 Like &amp; RT this tweet\n\u2705 Tag 1 frie\u2026"}, {"author_id": 1144746715569774592, "id": 1495250366417440769, "text": "RT @304verse: \ud83d\udc64: huening-ah if aliens invade earth you need to run away as quick as you can\n(img: if aliens invade, they will eat and captu\u2026"}, {"author_id": 1471069259233071106, "id": 1495250362454142976, "text": "RT @CryptoRonnin: \ud83c\udf81 HYPE ALIENS GIVEAWAY \ud83c\udf81\n\n\ud83d\udea8 1 NFT + 10 WL SPOTS \ud83d\udc7d\n\nHow to enter:\n\u2705 Follow @HYPEALIENS\n\u2705 Like &amp; RT this tweet\n\u2705 Tag 1 frie\u2026"}, {"author_id": 713761715356311556, "id": 1495250318589927427, "text": "RT @MainChannel_: '5\u2b50\ufe0f...elements of thrilling mystery, suspense, dystopian fantasy and science fiction.'\n\nThe Lenders Saga from @Travis_Bo\u2026"}, {"author_id": 1390986841000603658, "id": 1495250312336076803, "text": "RT @CryptoRonnin: \ud83c\udf81 HYPE ALIENS GIVEAWAY \ud83c\udf81\n\n\ud83d\udea8 1 NFT + 10 WL SPOTS \ud83d\udc7d\n\nHow to enter:\n\u2705 Follow @HYPEALIENS\n\u2705 Like &amp; RT this tweet\n\u2705 Tag 1 frie\u2026"}, {"author_id": 4061529973, "id": 1495250310566068231, "text": "RT @ufocustomrave: hello friends! Just made a Twitter account for my shoes! please retweet to spread the word \ud83d\udef8\u2728 I can paint any logo or de\u2026"}, {"author_id": 803311783, "id": 1495250308305461261, "text": "RT @fMRI_guy: Why do some people insist that ancient people were assisted by aliens when this idol clearly indicates that they were actuall\u2026"}, {"author_id": 1456474425654591492, "id": 1495250302152626178, "text": "RT @CryptoRonnin: \ud83c\udf81 HYPE ALIENS GIVEAWAY \ud83c\udf81\n\n\ud83d\udea8 1 NFT + 10 WL SPOTS \ud83d\udc7d\n\nHow to enter:\n\u2705 Follow @HYPEALIENS\n\u2705 Like &amp; RT this tweet\n\u2705 Tag 1 frie\u2026"}, {"author_id": 2429061716, "id": 1495250280061022208, "text": "So I\u2019m pretty sure I was abducted and probed by aliens"}, {"author_id": 229647723, "id": 1495250266358177793, "text": "@whimsah Ive had aliens that were vampires !"}, {"author_id": 1494320458316976129, "id": 1495250252940541958, "text": "RT @HYPEALIENS: HYPE ALIENS will be divided into different age groups and here is our Grandpa!\ud83d\udc74\n\nWanna be OG on our Discord? RT this \ud83d\udd25\n\n#NF\u2026"}, {"author_id": 1494981744059060224, "id": 1495250210632523782, "text": "RT @CryptoRonnin: \ud83c\udf81 HYPE ALIENS GIVEAWAY \ud83c\udf81\n\n\ud83d\udea8 1 NFT + 10 WL SPOTS \ud83d\udc7d\n\nHow to enter:\n\u2705 Follow @HYPEALIENS\n\u2705 Like &amp; RT this tweet\n\u2705 Tag 1 frie\u2026"}, {"author_id": 1484919724370984960, "id": 1495250208095092741, "text": "RT @CryptoRonnin: \ud83c\udf81 HYPE ALIENS GIVEAWAY \ud83c\udf81\n\n\ud83d\udea8 1 NFT + 10 WL SPOTS \ud83d\udc7d\n\nHow to enter:\n\u2705 Follow @HYPEALIENS\n\u2705 Like &amp; RT this tweet\n\u2705 Tag 1 frie\u2026"}, {"author_id": 1471835335281709061, "id": 1495250202181070855, "text": "RT @CryptoRonnin: \ud83c\udf81 HYPE ALIENS GIVEAWAY \ud83c\udf81\n\n\ud83d\udea8 1 NFT + 10 WL SPOTS \ud83d\udc7d\n\nHow to enter:\n\u2705 Follow @HYPEALIENS\n\u2705 Like &amp; RT this tweet\n\u2705 Tag 1 frie\u2026"}, {"author_id": 882849595147071489, "id": 1495250198620221444, "text": "@DHSgov TIP:  stop flying illegal aliens into our communities."}, {"author_id": 1474430342098407424, "id": 1495250198591045637, "text": "RT @CryptoRonnin: \ud83c\udf81 HYPE ALIENS GIVEAWAY \ud83c\udf81\n\n\ud83d\udea8 1 NFT + 10 WL SPOTS \ud83d\udc7d\n\nHow to enter:\n\u2705 Follow @HYPEALIENS\n\u2705 Like &amp; RT this tweet\n\u2705 Tag 1 frie\u2026"}, {"author_id": 1421844276988678147, "id": 1495250194640011265, "text": "RT @CryptoRonnin: \ud83c\udf81 HYPE ALIENS GIVEAWAY \ud83c\udf81\n\n\ud83d\udea8 1 NFT + 10 WL SPOTS \ud83d\udc7d\n\nHow to enter:\n\u2705 Follow @HYPEALIENS\n\u2705 Like &amp; RT this tweet\n\u2705 Tag 1 frie\u2026"}, {"author_id": 1495024609875406858, "id": 1495250164386258944, "text": "New Batch Of Unique Aliens ! https://t.co/ga7rwKSYKN via @opensea"}, {"author_id": 1494480688426684417, "id": 1495250133419986953, "text": "RT @CryptoRonnin: \ud83c\udf81 HYPE ALIENS GIVEAWAY \ud83c\udf81\n\n\ud83d\udea8 1 NFT + 10 WL SPOTS \ud83d\udc7d\n\nHow to enter:\n\u2705 Follow @HYPEALIENS\n\u2705 Like &amp; RT this tweet\n\u2705 Tag 1 frie\u2026"}, {"author_id": 1479990302899261443, "id": 1495250130202931200, "text": "RT @CryptoRonnin: \ud83c\udf81 HYPE ALIENS GIVEAWAY \ud83c\udf81\n\n\ud83d\udea8 1 NFT + 10 WL SPOTS \ud83d\udc7d\n\nHow to enter:\n\u2705 Follow @HYPEALIENS\n\u2705 Like &amp; RT this tweet\n\u2705 Tag 1 frie\u2026"}, {"author_id": 775546770172485633, "id": 1495250106668535810, "text": "@ABC7 I'm not saying it's aliens but it's aliens..."}, {"author_id": 1471047568280879109, "id": 1495250103593881607, "text": "RT @CryptoRonnin: \ud83c\udf81 HYPE ALIENS GIVEAWAY \ud83c\udf81\n\n\ud83d\udea8 1 NFT + 10 WL SPOTS \ud83d\udc7d\n\nHow to enter:\n\u2705 Follow @HYPEALIENS\n\u2705 Like &amp; RT this tweet\n\u2705 Tag 1 frie\u2026"}, {"author_id": 1219746456568860672, "id": 1495250092697300996, "text": "@P8R1OT_PARADOX Progressive liberal politicians honor crime and criminals and loathe law and order, deny God with multiple genders, call you racist while favoring one race, transport illegal aliens across the country under the cover of night, call you hero then villan in a two year span."}, {"author_id": 166868798, "id": 1495250078256316418, "text": "RT @DonnaCorrales9: mint some before they run out of aliens @alienenemes #nftart NFTs https://t.co/fNJDvNtVRq"}, {"author_id": 716637086749704192, "id": 1495250037709754373, "text": "A bunch of aliens appeared in New York City and scared the hell out of a group of schoolkids"}, {"author_id": 1476795717284859905, "id": 1495250018030211075, "text": "mint some before they run out of aliens @alienenemes #NFT #NFTCommunity https://t.co/0dVDzZA7jd"}, {"author_id": 1487414803438391297, "id": 1495250002842693634, "text": "grab your aliens cheap 0.01 ETH @alienenemes #NFTProject #nft https://t.co/9DZgeZH6pU"}, {"author_id": 1299673800, "id": 1495249999399112704, "text": "RT @DrAliSKhan: Are octopus aliens? 2018 paper.\nhttps://t.co/IAPfDwU5kV"}]