[{"author_id": 1019079486833389568, "id": 1495250513373315073, "text": "RT @isekaiviolet: at last but not least.. here is annie as princess mononoke, I can't get rid  off her in my mind so I went to my desk and\u2026"}, {"author_id": 2881936228, "id": 1495248875317338118, "text": "RT @PhaustoK: Ashitaka from Princess Mononoke \ud83d\ude0b\n#NSFW #Gay #Bara #Yaoi https://t.co/soYjd2tunP"}, {"author_id": 40525564, "id": 1495246140077395971, "text": "Princess Mononoke is still a damn good movie"}, {"author_id": 2511580910, "id": 1495243144014831621, "text": "I need to talk about how I hated the ending of princess mononoke. Who\u2019s seen it?"}, {"author_id": 2575124042, "id": 1495242714908037121, "text": "The non-rock or metal pins in my vest tonight. \n\nLegend of Zelda\nKill La Kill\nPrincess Mononoke\nLast Podcast on the Left https://t.co/afJE48IJZB"}, {"author_id": 1304472307562426368, "id": 1495241660111855616, "text": "RT @isekaiviolet: at last but not least.. here is annie as princess mononoke, I can't get rid  off her in my mind so I went to my desk and\u2026"}, {"author_id": 1184919062490402816, "id": 1495240448822050818, "text": "Have you seen Princess Mononoke? https://t.co/WUYCpGlvBk"}, {"author_id": 959986179432103936, "id": 1495239746079309824, "text": "@myelessar I've found a way to somewhat replicate that effect - don't consume the content for a while, and then just before you go back to it consume a bunch of media from the same time period (eg music, TV ads, movies etc) - I tried it with Princess Mononoke and it was mind-blowing \ud83e\udd70"}, {"author_id": 2605126445, "id": 1495239715422932996, "text": "RT @Cris263383341: \ud83d\udc3aOne of the best movies Princess Mononoke\ud83d\udc3a\nConfirm with RT\ud83d\udd01and MG\u2764\ufe0fit was for you too https://t.co/XEpJQgDO8A"}, {"author_id": 2941199713, "id": 1495239590449672202, "text": "@Madison420Ivy princess mononoke, it's a good story line for it's time and beautiful animation."}, {"author_id": 1432561006899834881, "id": 1495238843649323015, "text": "princess mononoke was published in the year, 2002 right or wrong? Naruto Shippuden Showdown  match Rock Lee VS Dengaku"}, {"author_id": 1480782607826579457, "id": 1495235820550193156, "text": "RT @Cris263383341: \ud83d\udc3aOne of the best movies Princess Mononoke\ud83d\udc3a\nConfirm with RT\ud83d\udd01and MG\u2764\ufe0fit was for you too https://t.co/XEpJQgDO8A"}, {"author_id": 1438265907831246850, "id": 1495229856258265095, "text": "RT @ZinNeverDies: Ever wished you could roleplay in the world of Princess Mononoke? How about dark fantasy settings like The Witcher books?\u2026"}, {"author_id": 946213609813749761, "id": 1495226024249942022, "text": "RT @KajCreates: Happy to announce my 1st mint on Foundation! Here is an ode to may favourite Miyazaki film Princess Mononoke.\n\nThis is \u201cWol\u2026"}, {"author_id": 2608952667, "id": 1495223147464900610, "text": "RT @isekaiviolet: at last but not least.. here is annie as princess mononoke, I can't get rid  off her in my mind so I went to my desk and\u2026"}, {"author_id": 1096379142277398528, "id": 1495221165756977154, "text": "My mom is going to be very confused when she sees I made my HBO Max profile picture a kodama from Princess Mononoke. \ud83d\ude2d"}, {"author_id": 1395824717420969987, "id": 1495219680746737664, "text": "RT @isekaiviolet: at last but not least.. here is annie as princess mononoke, I can't get rid  off her in my mind so I went to my desk and\u2026"}, {"author_id": 1404606635964731394, "id": 1495218552923512836, "text": "RT @isekaiviolet: at last but not least.. here is annie as princess mononoke, I can't get rid  off her in my mind so I went to my desk and\u2026"}, {"author_id": 1449850902181990406, "id": 1495217322197278722, "text": "RT @Cris263383341: \ud83d\udc3aOne of the best movies Princess Mononoke\ud83d\udc3a\nConfirm with RT\ud83d\udd01and MG\u2764\ufe0fit was for you too https://t.co/XEpJQgDO8A"}, {"author_id": 1493984072271802369, "id": 1495217321996013568, "text": "Princess Mononoke FANART from a Studio Ghibli film. She was infected by the Tatarigami's curse and it was different for her as she was turned into the wolf like she was raised to and became mutant. \ud83e\uddea\n\nShikii#8273\n@MutantShibaClub @berrytheartist @crazyJUUMP @Gaba8545 @LordSlabs https://t.co/FLe20D0zSn"}, {"author_id": 1394683070968647680, "id": 1495217279323287560, "text": "RT @ghiblipicture: Princess Mononoke (1997) https://t.co/9D7Ue8E267"}, {"author_id": 1394683070968647680, "id": 1495217252534210562, "text": "RT @ghiblipicture: Princess Mononoke (1997) https://t.co/ir8w3g8X0p"}, {"author_id": 204901237, "id": 1495215845655592960, "text": "Dropping the daughter off at Katsucon, as Princess Mononoke. https://t.co/0ZpZvh6I0F"}, {"author_id": 1493750060655341574, "id": 1495214677072171008, "text": "RT @incredi16092108: \ud83d\udc3aOne of the best movies Princess Mononoke\ud83d\udc3a\nConfirm with RT\ud83d\udd01and MG\u2764\ufe0fit was for you too\n\ud83d\udc3a@incredi16092108\ud83d\udc3a https://t.co/\u2026"}, {"author_id": 1331202425261236224, "id": 1495213260655972352, "text": "RT @isekaiviolet: at last but not least.. here is annie as princess mononoke, I can't get rid  off her in my mind so I went to my desk and\u2026"}, {"author_id": 1141353276908195842, "id": 1495209781937717250, "text": "Top 10 films anime\n1. Les enfants Loups\n2. Howl\u2019s moving castle\n3. A whisker away\n4. Josee the tiger and the fish\n5. Spirited away\n6. Doukyuusei\n7. Stranger of the beach\n8. From up on Poppy hill\n9. Princess mononoke\n10. Silent voice"}, {"author_id": 1396120526398033922, "id": 1495209654128939012, "text": "RT @WerewolfLiker: Wife and I made a list of our pick for the best film of each year in the 90s.\n\n1990: Tremors\n1991: Terminator 2\n1992: Un\u2026"}, {"author_id": 1465762047766024199, "id": 1495209488193892357, "text": "RT @90sArt_: Princess Mononoke (1997) https://t.co/LrnFbmFUh7"}, {"author_id": 847892924838940673, "id": 1495208941520703488, "text": "@RavMedic @soft_scout I had someone buy me four little Tree Spirits from Princess Mononoke. It'd be only fair to have some spirit friends."}, {"author_id": 1245506797332385793, "id": 1495208870062473220, "text": "This is my princess damsel, appropriately named Mononoke. She's very pretty, but very territorial and kind of a bitch #aquarium #saltwaterfish https://t.co/toXNclnMKw"}, {"author_id": 1945129729, "id": 1495208500405878787, "text": "@ImoveCar I've virtually finished all that I plan on watching! \nmy neighbor totoro, spirited away, whisper of the heart, princess mononoke, kiki's delivery service, howl's moving castle, ponyo &amp;\nI'm mid-way through Castle in the Sky!"}, {"author_id": 439535387, "id": 1495205515600744448, "text": "RT @Cris263383341: \ud83d\udc3aOne of the best movies Princess Mononoke\ud83d\udc3a\nConfirm with RT\ud83d\udd01and MG\u2764\ufe0fit was for you too https://t.co/XEpJQgDO8A"}, {"author_id": 798752248356405248, "id": 1495202286653562890, "text": "RT @AnimetatezakiE: Mv formative experience-18\nThe making video of Princess Mononoke that I watched repeatedly when I was in junior high sc\u2026"}, {"author_id": 1366224048389201925, "id": 1495201617540366336, "text": "Mv formative experience-18\nThe making video of Princess Mononoke that I watched repeatedly when I was in junior high school and high school.\nProbably I had a longing for the animation industry when I saw the masters working at Studio Ghibli. https://t.co/Qq8bI3J2Fy"}, {"author_id": 1380913306865528839, "id": 1495199805349548032, "text": "@morenaspicy @dellieisla Princess Mononoke?"}, {"author_id": 45212332, "id": 1495198097533816838, "text": "@funimationUK Neon Genesis Evangelion\nDemon Slayer\nPrincess Mononoke"}, {"author_id": 760440478575816704, "id": 1495194911544651779, "text": "@meowmeowmeowrr_ @MrReevo Princess Mononoke"}, {"author_id": 1490499408022102018, "id": 1495194584200060930, "text": "RT @isekaiviolet: at last but not least.. here is annie as princess mononoke, I can't get rid  off her in my mind so I went to my desk and\u2026"}, {"author_id": 1333788044298571782, "id": 1495194374560530443, "text": "RT @virtualangeIs: princess mononoke (1997) https://t.co/rZuljZ9ugO"}, {"author_id": 1490144251501555715, "id": 1495193330535313414, "text": "RT @Cris263383341: \ud83d\udc3aOne of the best movies Princess Mononoke\ud83d\udc3a\nConfirm with RT\ud83d\udd01and MG\u2764\ufe0fit was for you too https://t.co/XEpJQgDO8A"}, {"author_id": 1415784383730962432, "id": 1495191712540422151, "text": "@funimationUK Cowboy Bebop, Naruto: Shippuden, and\u2026 Princess Mononoke. Are anime movies allowed? Lol"}, {"author_id": 1471742618182762500, "id": 1495190021502029826, "text": "RT @Cris263383341: \ud83d\udc3aOne of the best movies Princess Mononoke\ud83d\udc3a\nConfirm with RT\ud83d\udd01and MG\u2764\ufe0fit was for you too https://t.co/XEpJQgDO8A"}, {"author_id": 1337724480425242629, "id": 1495187282663378945, "text": "RT @Cris263383341: \ud83d\udc3aOne of the best movies Princess Mononoke\ud83d\udc3a\nConfirm with RT\ud83d\udd01and MG\u2764\ufe0fit was for you too https://t.co/XEpJQgDO8A"}, {"author_id": 1047080543853133824, "id": 1495187043512692739, "text": "my next will probably be the wind rises of princess mononoke"}, {"author_id": 612659974, "id": 1495185971243008007, "text": "RT @Cris263383341: \ud83d\udc3aOne of the best movies Princess Mononoke\ud83d\udc3a\nConfirm with RT\ud83d\udd01and MG\u2764\ufe0fit was for you too https://t.co/XEpJQgDO8A"}, {"author_id": 1324466485616660481, "id": 1495185146575822851, "text": "O melhor do Ghibli\n\nMy \u2605\u2605\u2605\u2605\u2605 review of Princess Mononoke on Letterboxd https://t.co/FKYzGvQsbL"}, {"author_id": 548135436, "id": 1495184578411171841, "text": "and he also mutilated by Princess Mononoke poster"}, {"author_id": 1460275931399004165, "id": 1495183641869271043, "text": "RT @Cris263383341: \ud83d\udc3aOne of the best movies Princess Mononoke\ud83d\udc3a\nConfirm with RT\ud83d\udd01and MG\u2764\ufe0fit was for you too https://t.co/XEpJQgDO8A"}, {"author_id": 1452351863890890755, "id": 1495183073423486976, "text": "RT @Cris263383341: \ud83d\udc3aOne of the best movies Princess Mononoke\ud83d\udc3a\nConfirm with RT\ud83d\udd01and MG\u2764\ufe0fit was for you too https://t.co/XEpJQgDO8A"}, {"author_id": 1452351863890890755, "id": 1495183023779692545, "text": "RT @incredi16092108: \ud83d\udc3aOne of the best movies Princess Mononoke\ud83d\udc3a\nConfirm with RT\ud83d\udd01and MG\u2764\ufe0fit was for you too\n\ud83d\udc3a@incredi16092108\ud83d\udc3a https://t.co/\u2026"}, {"author_id": 1487179494280642564, "id": 1495182128992108549, "text": "RT @incredi16092108: \ud83d\udc3aOne of the best movies Princess Mononoke\ud83d\udc3a\nConfirm with RT\ud83d\udd01and MG\u2764\ufe0fit was for you too\n\ud83d\udc3a@incredi16092108\ud83d\udc3a https://t.co/\u2026"}, {"author_id": 1487179494280642564, "id": 1495182103876706311, "text": "RT @Cris263383341: \ud83d\udc3aOne of the best movies Princess Mononoke\ud83d\udc3a\nConfirm with RT\ud83d\udd01and MG\u2764\ufe0fit was for you too https://t.co/XEpJQgDO8A"}, {"author_id": 1409591235556356099, "id": 1495181715039526915, "text": "RT @Cris263383341: \ud83d\udc3aOne of the best movies Princess Mononoke\ud83d\udc3a\nConfirm with RT\ud83d\udd01and MG\u2764\ufe0fit was for you too https://t.co/XEpJQgDO8A"}, {"author_id": 1432561006899834881, "id": 1495180885896810499, "text": "princess mononoke was published in the year, 2011 right or wrong? Naruto Shippuden Showdown  match Hayase VS Harusame"}, {"author_id": 1490473401609342978, "id": 1495180804854480896, "text": "RT @incredi16092108: \ud83d\udc3aOne of the best movies Princess Mononoke\ud83d\udc3a\nConfirm with RT\ud83d\udd01and MG\u2764\ufe0fit was for you too\n\ud83d\udc3a@incredi16092108\ud83d\udc3a https://t.co/\u2026"}, {"author_id": 1482066273332772869, "id": 1495180280730202113, "text": "RT @Cris263383341: \ud83d\udc3aOne of the best movies Princess Mononoke\ud83d\udc3a\nConfirm with RT\ud83d\udd01and MG\u2764\ufe0fit was for you too https://t.co/XEpJQgDO8A"}, {"author_id": 1060672032, "id": 1495180105047416839, "text": "RT @Cris263383341: \ud83d\udc3aOne of the best movies Princess Mononoke\ud83d\udc3a\nConfirm with RT\ud83d\udd01and MG\u2764\ufe0fit was for you too https://t.co/XEpJQgDO8A"}, {"author_id": 1490473401609342978, "id": 1495179972113170432, "text": "RT @Cris263383341: \ud83d\udc3aOne of the best movies Princess Mononoke\ud83d\udc3a\nConfirm with RT\ud83d\udd01and MG\u2764\ufe0fit was for you too https://t.co/XEpJQgDO8A"}, {"author_id": 1472089206042288128, "id": 1495179951066140674, "text": "RT @Cris263383341: \ud83d\udc3aOne of the best movies Princess Mononoke\ud83d\udc3a\nConfirm with RT\ud83d\udd01and MG\u2764\ufe0fit was for you too https://t.co/XEpJQgDO8A"}, {"author_id": 1491476593356779527, "id": 1495179390581411842, "text": "\ud83d\udc3aOne of the best movies Princess Mononoke\ud83d\udc3a\nConfirm with RT\ud83d\udd01and MG\u2764\ufe0fit was for you too https://t.co/XEpJQgDO8A"}, {"author_id": 281676046, "id": 1495178715336216579, "text": "RT @ZinNeverDies: @curiouspenguin Ever wished you could roleplay in the world of Princess Mononoke? How about dark fantasy settings like Th\u2026"}, {"author_id": 1445636616492486660, "id": 1495178714023354368, "text": "RT @snowchiId_: just finished princess mononoke https://t.co/HRnpWPMM4I"}, {"author_id": 4364007438, "id": 1495178039566782466, "text": "RT @VideoArtGame: Illustration | Princess Mononoke\n\nArtist: @pix_bun https://t.co/4fKmv10SlQ"}, {"author_id": 1432454586971918338, "id": 1495177932414795779, "text": "\ud83d\udc3aOne of the best movies Princess Mononoke\ud83d\udc3a\nConfirm with RT\ud83d\udd01and MG\u2764\ufe0fit was for you too\n\ud83d\udc3a@incredi16092108\ud83d\udc3a https://t.co/oZVGY77zqV"}, {"author_id": 1258985656576929793, "id": 1495177358315499520, "text": "RT @wunderkammern_: GN! \n\u2014\nprincess mononoke. kodama roh pohon sedang beristirahat \ud83d\ude34\n\u2014\non this is my old artwork, i still use the old signa\u2026"}, {"author_id": 1143556867702034433, "id": 1495175774713831428, "text": "@marsymartian You\u2019re showing your titties and have a Princess Mononoke tattoo?! Are we soul sisters?! \ud83d\udc96"}, {"author_id": 1229869982324076548, "id": 1495173885007958020, "text": "just finished princess mononoke https://t.co/HRnpWPMM4I"}, {"author_id": 1364330908002746372, "id": 1495173364880658436, "text": "@iam_anonymous3 This is really cool, makes me think of the scene in princess mononoke when the forest spirit dies and it's head starts turning to goop.  Well done!"}, {"author_id": 726950470808260609, "id": 1495171805685829634, "text": "Just watched Princess Mononoke, Cringe. 0/5"}, {"author_id": 1309612106338250753, "id": 1495170266942611456, "text": "I watched Nausica\u00e4 for the first time about a week ago and I have not been able to stop thinking about it.  I had previously only seen Princess Mononoke and Spirited Away and I am forced to think I may not have been ready for Miyazaki's films until this point in my life."}, {"author_id": 1443392421677703169, "id": 1495165889351671816, "text": "RT @VideoArtGame: Illustration | Princess Mononoke\n\nArtist: @pix_bun https://t.co/4fKmv10SlQ"}, {"author_id": 721032869439762433, "id": 1495165092928933888, "text": "-being a fan of its obnoxiously fast-paced tone or the voices of said characters? Idk, have you ever stopped and thought really hard about why we're possibly being critical towards it that doesn't once mention a single lick of it not fucking being Princess Mononoke? Lol."}, {"author_id": 1017366094254886912, "id": 1495164505915015174, "text": "RT @ZinNeverDies: Ever wished you could roleplay in the world of Princess Mononoke? How about dark fantasy settings like The Witcher books?\u2026"}, {"author_id": 14435983, "id": 1495163378368757767, "text": "@DustyofPodunk Studio Ghibli are basically Japanese Disney. They even have a deal with Disney to have them dubbed the films into English. They are all beautiful, I think Princess Mononoke is one of the more violent ones, Most are just beautiful and an escape"}, {"author_id": 2782478520, "id": 1495163197732663297, "text": "RT @VideoArtGame: Illustration | Princess Mononoke\n\nArtist: @danielwarrenart https://t.co/e4GMxc4xKV"}, {"author_id": 98519454, "id": 1495162037990830082, "text": "Movie 9 of 52 watched for the year \nPrincess Mononoke\nDONT.FUCK.WITH.NATURE!\nI had no expectations going into this but this movie was beautiful! Sometimes disgustingly so. The animation is so butter smooth and wasnt expecting the level of violence. https://t.co/0sxjcYSfdH"}, {"author_id": 1377888682691022851, "id": 1495161935788068864, "text": "RT @isekaiviolet: at last but not least.. here is annie as princess mononoke, I can't get rid  off her in my mind so I went to my desk and\u2026"}, {"author_id": 1441266009113907216, "id": 1495161855794302979, "text": "@CardanoWaifus PRINCESS MONONOKE\nBECAUSE OBVI I WOULD BE SAN AND WOLF BROTHERS YOU CAN RIDE??? 2 TAIL MONSTER MOM??\npls"}, {"author_id": 737202059196391424, "id": 1495160680210698250, "text": "Wife and I made a list of our pick for the best film of each year in the 90s.\n\n1990: Tremors\n1991: Terminator 2\n1992: Unforgiven\n1993: Jurassic Park\n1994: The Professional\n1995: Rumble in the Bronx\n1996: Muppet Treasure Island\n1997: Princess Mononoke\n1998: Ronin\n1999: The Matrix"}, {"author_id": 1420123541677252613, "id": 1495157253690863618, "text": "RT @virtualangeIs: princess mononoke (1997) https://t.co/rZuljZ9ugO"}, {"author_id": 828286998519635968, "id": 1495156136953135106, "text": "@thestanceman1 - Palm Springs / Prime\n- The Rescue / sehr stark Doku / D+\n- The Last Black Man Black Man In San Francisco / Prime\n- Princess Mononoke / Mein absoluter Lieblingsanime / Netflix\n- American Psycho / Netflix\n- Good Will Hunting / Irgendein Streaming Dienst\n- Der Rausch\n..."}, {"author_id": 1450815301172535296, "id": 1495153488288002048, "text": "@Prxmiseiwnl Princess Mononoke"}]