[{"author_id": 1467754052347785219, "id": 1495252809326891008, "text": "#YUTA will be on the cover of NUMERO TOKYO on Feb. 26th which will contain a 16 page interview and fashion story. Please look forward to it!\n\nPREORDER:\n https://t.co/7FkBsA3SRu"}, {"author_id": 173777571, "id": 1495251607709118467, "text": "8. I saw someone said \"Night at the Museum\" ride is boring, and I have to disagree. This ride is the same concept as Tokyo DisneySea\u2019s Toy Story ride and it is DisneySea\u2019s most popular ride. A 2-player ride. It will probably be boring if you are going alone."}, {"author_id": 858888940073492480, "id": 1495243460307079168, "text": "Movie idea: Breathless by Jean-Luc Godard with a little bit of Tokyo Story with a stronger beginning"}]