[{"author_id": 76791141, "id": 1495251678987231239, "text": "RT @ThisIsColbert: Skwatta Kamp went - if the shoe fits \ud83d\ude2d\nI know your fav took offence in this\n\n\"Now they put millions on it just to be the\u2026"}, {"author_id": 1058589102394662913, "id": 1495251678731583488, "text": "anyways , if your\nname is lee tae-hyeok , \nhit me up right now ."}, {"author_id": 1271334799911739392, "id": 1495251676101419008, "text": "RT @Nathuram_patel1: Must know the reality about, who the Real God is, what is His name and how can we attain Him?\nGet all your answers in\u2026"}, {"author_id": 1380391419815337984, "id": 1495251674390216704, "text": "no because bigots nowadays have two pinto-beans for brains\u2026 y\u2019all say and do the most bigoted shit with your name, face, and entire business attached\u2026 like that digital footprint is EMBARRASSING."}, {"author_id": 892605338284838913, "id": 1495251672775282691, "text": "@japrst It's almost like you were drawing something at school, you put your name on it and stuff, and you lost it, but now someone's walking around with your drawing and just showing it around like \"Look at this, this guy's art is amazing!\" \n\nJust describing it sounds really awkward."}, {"author_id": 456212171, "id": 1495251669508141057, "text": "RT @atl_name: As an aspiring writer, people like this are the ones that scare me the most. I don't want to publish anything of my creation\u2026"}, {"author_id": 1292150163138437122, "id": 1495251668321337348, "text": "RT @DinshawOfficial: Find the identical ice cream scoops of Delicious Dinshaw's ice cream\nFollow DINSHAW'S on all the platforms\nShare the p\u2026"}, {"author_id": 963618197323862018, "id": 1495251665762480129, "text": "@DelhiJalBoard @uditprakash For redressal of your complaint could you please help us with the following\nNAME: p p mehata\nADDRESS:136,B gulabi bagh\nCONTACT NO.: 9311155449\nKNO: 1827601000\nZone: cz2 / Prasad nagar\nIssue: we are not getting bills, please reverse late fees has not been adjusted 176.81 and 40.48"}, {"author_id": 1080460761737191425, "id": 1495251663036243974, "text": "RT @deadpoet______: may you attract good people with good intentions who help you become your best version. who celebrate your growth like\u2026"}, {"author_id": 1493683226849644545, "id": 1495251653871562752, "text": "Do not engage with his acc\u2019s don\u2019t QT him/ only take screenshots and report his tweets. Lock your accounts down if you need to and be sure to have two factor verification on twitter/ any other social media associated w your twitter handle or name if it\u2019s public"}, {"author_id": 1493386183971377152, "id": 1495251644526776321, "text": "\u1160\n\n\u1160\u1160 ' that is no way to treat a former God, boy. Tell me your name '\n\n\u1160\u1160 whipping a crimson gaze around to face the Kizuki in his presence. A strange look. . . 6 eyes. . . A purple haori, and pale skin. . . \n\n\u1160 https://t.co/duaBYH1hZq https://t.co/zAfn4EgQls"}, {"author_id": 1483289761968271371, "id": 1495251641607626755, "text": "RT @C_Mulroney: Family Day weekend is free #FamilyFishingWeekend in Ontario!\n\nDon't forget your government issued photo ID that states your\u2026"}, {"author_id": 1475728708627537920, "id": 1495251631008538627, "text": "@chidinmaekile Good morning woman of God. My name is Raphael George. I have been soliciting for your help through out the month via your tweets. I haven't been able to renew my rent and I will be forced out this week. Please I need your help. I hope this gets to you. God bless"}, {"author_id": 1330898857291522048, "id": 1495251630077321221, "text": "RT @yedam_kr: 220219\n\ud83d\udc64: ah sorry~ i forgot your name\n\ud83e\udd8a: oh im BANG YEDAM\n\ud83d\udc64: no~ no~ can i call you mine?\n\ud83e\udd8a: *shocked* oh yeahh *laughs*\n\nHE\u2026"}, {"author_id": 473072157, "id": 1495251626621542400, "text": "\"Roxas... Do you remember your true name?\" - Namine (KH 2)"}, {"author_id": 1449377813761429509, "id": 1495251623551004675, "text": "RT @yedam_kr: 220219\n\ud83d\udc64: ah sorry~ i forgot your name\n\ud83e\udd8a: oh im BANG YEDAM\n\ud83d\udc64: no~ no~ can i call you mine?\n\ud83e\udd8a: *shocked* oh yeahh *laughs*\n\nHE\u2026"}, {"author_id": 86935017, "id": 1495251622259310594, "text": "@Joseph45290266 If you\u2019re so proud why don\u2019t you show your name or face?"}, {"author_id": 1249603647736078341, "id": 1495251621386801153, "text": "RT @newvisionwire: We pray,\nDear Father, thank You for seeing us through yet another peaceful night. We pray for the spirit of love &amp; coope\u2026"}, {"author_id": 1485337302306111490, "id": 1495251618870218754, "text": "@Sarahbeachdays Peace be upon you, my dear, my greetings to you, my name is Saleh Mustafa, Ya\nMy beloved and dear lady, and may God bless you and I hope that you accept\nMy friendship is with you, you and I, and thank you very much for your presence\n   salhgmhh123@///gmail.///com"}, {"author_id": 3624658394, "id": 1495251614571061248, "text": "RT @TLD_Owner: #HNS Nameboard just got an upgrade !\n- supports HTTPS with DANE (https://hns.nameboard)\n- use a TLD you truly own to create\u2026"}, {"author_id": 871361492624568321, "id": 1495251613723807746, "text": "Eilen Jewell - Where They Never Say Your Name"}, {"author_id": 1489783533740695556, "id": 1495251612092272641, "text": "RT @MSF_USA: This Valentine\u2019s Day, will you join us in sending a message of love and gratitude to the Doctors Without Borders medical teams\u2026"}, {"author_id": 1071836103844347905, "id": 1495251611333058570, "text": "RT @_meow___meow__: Remove \"J\" from Jimin &amp; add the first letter of your name"}, {"author_id": 1281497408161984513, "id": 1495251608942219264, "text": "RT @enzosalad: So my dad is a Ferdinand Marcos apologist but will not vote BBM. I asked why? And he said , \u201cparang ikaw- you made a name fo\u2026"}, {"author_id": 1299431736628056064, "id": 1495251602281697284, "text": "RT @_meow___meow__: Remove \"J\" from Jimin &amp; add the first letter of your name"}, {"author_id": 1462402602612641794, "id": 1495251595801800704, "text": "@starlightmoon07 areee i knowwwww, just didn't know your name"}, {"author_id": 963618197323862018, "id": 1495251594006302720, "text": "@DelhiJalBoard @uditprakash @CMODelhi @SatyendarJain @raghav_chadha For redressal of your complaint could you please help us with the following\nNAME: p p mehata\nADDRESS:136,B gulabi bagh\nCONTACT NO.: 9311155449\nKNO: 1827601000\nZone: cz2 / Prasad nagar\nIssue: we are not getting bills, please reverse late fees has not been adjusted 176.81 and 40.48"}, {"author_id": 82151473, "id": 1495251593113001986, "text": "@itzme1510 I understand and apologize for any difficulty. Please send us a DM here with additional details, your name as it appears on the account and a contact number. Do not provide any account numbers or PINs. Also, please delete your message containing your phone number. ^Kyle https://t.co/gvC4jAOA9c"}, {"author_id": 1302506872168046592, "id": 1495251590932238336, "text": "RT @elyshmi: keep my name out of your bloody mouth."}, {"author_id": 1471023897847889921, "id": 1495251575631011844, "text": "RT @nickmusk21: We just launched our new Personalized Name Ring! \u2728 \ud83d\udc97\nShow your love by wearing the names of your loved ones close to you. h\u2026"}, {"author_id": 1573116356, "id": 1495251567133749250, "text": "RT @yedam_kr: 220219\n\ud83d\udc64: ah sorry~ i forgot your name\n\ud83e\udd8a: oh im BANG YEDAM\n\ud83d\udc64: no~ no~ can i call you mine?\n\ud83e\udd8a: *shocked* oh yeahh *laughs*\n\nHE\u2026"}, {"author_id": 965399650248351744, "id": 1495251565908836355, "text": "RT @EstVallChorale: \u201cThe Lord is a refuge for the oppressed, a stronghold in times of trouble. Those who know your name trust in you, for y\u2026"}, {"author_id": 1059289708516249601, "id": 1495251561223708683, "text": "If I have an emoji by your name and I find out you removed mine or didn\u2019t put one by my name I\u2019m removing yours"}, {"author_id": 1411705178869448707, "id": 1495251560644976640, "text": "Keep my pretty name out of your mouth \u2661"}, {"author_id": 1180598498405879808, "id": 1495251558153469953, "text": "RT @Cre8tivejcakes: If I hear say you know put aunty for my name ehnnnnn, I go wunjure you... I no be your mate ooo. @Symply_Tacha My queen\u2026"}, {"author_id": 2815754953, "id": 1495251557545304065, "text": "@SumitGo30271596 We are sorry to hear about your experience. Please send us a DM with the phone number &amp; email address associated with your account, and order details like date and time of the order with restaurant name or order id, so that we can assist you further. Waiting for your response. https://t.co/sd7yH5jmbJ"}, {"author_id": 1297352746484391937, "id": 1495251541116153860, "text": "RT @yedam_kr: 220219\n\ud83d\udc64: ah sorry~ i forgot your name\n\ud83e\udd8a: oh im BANG YEDAM\n\ud83d\udc64: no~ no~ can i call you mine?\n\ud83e\udd8a: *shocked* oh yeahh *laughs*\n\nHE\u2026"}, {"author_id": 1326015969014083584, "id": 1495251529258864645, "text": "RT @Ninx002_: Good Morning my goats\ud83d\udc10\n\nYesterday I had the 'YOUR NAME' experience irl and some girl was inside my body and was tweeting yest\u2026"}, {"author_id": 801203611, "id": 1495251522267013127, "text": "@Veganella_ To report I would need your Facebook name. Sorry I'm just recently back on FB and not very good with this"}, {"author_id": 635746994, "id": 1495251521516228611, "text": "RT @deadpoet______: may you attract good people with good intentions who help you become your best version. who celebrate your growth like\u2026"}, {"author_id": 721919593485217792, "id": 1495251517984575488, "text": "@Ant7nIivrLqtvlv If you apply under the name of your favorite artist and win, you will receive 1 million won or a prize."}, {"author_id": 1487208279059038209, "id": 1495251512980688900, "text": "RT @deadpoet______: may you attract good people with good intentions who help you become your best version. who celebrate your growth like\u2026"}, {"author_id": 293904230, "id": 1495251508161568771, "text": "When you write your cat's name in place of the main character's in your own script, it's time to clock out."}, {"author_id": 1219531565178462208, "id": 1495251503128449024, "text": "RT @deadpoet______: may you attract good people with good intentions who help you become your best version. who celebrate your growth like\u2026"}, {"author_id": 44458662, "id": 1495251481259294720, "text": "@lavenderfeeIs Hello Ash. We\u2019re concerned to hear this and we want to learn more. Please DM us with your full name, confirmation #, email and telephone number. Feel free to include any additional details as well. Warm regards -Julie"}, {"author_id": 1314784381676945409, "id": 1495251480944783360, "text": "RT @IndigoEternal: \ud83d\udcab FREE LOVE GUIDANCE \ud83d\udcab\nOne card tarot pull for general love advice. Must be following, RT, and react to this post. Pleas\u2026"}, {"author_id": 1420167061477724160, "id": 1495251471759298561, "text": "@KayIaAgain That\u2019s your name ?"}, {"author_id": 1464430287589363714, "id": 1495251471021096961, "text": "@TryingBea \u201cOh yeah nya, I totally am! I\u2019m Cyan it\u2019s nice to meet you, just transferred from England a few days ago.\u201d\n\nShe held out a hand with a bright smile on her face, bright and chipper as ever\n\n\u201cWell I\u2019d love to know your name if you\u2019ll tell me.\u201d"}, {"author_id": 1259577887952384000, "id": 1495251469997682692, "text": "If your name is Aiden or is any varient of the name Aiden, I don't even know man."}, {"author_id": 844532384196382720, "id": 1495251456462622728, "text": "RT @deadpoet______: may you attract good people with good intentions who help you become your best version. who celebrate your growth like\u2026"}, {"author_id": 1425458645152718853, "id": 1495251451521941506, "text": "RT @SagarRithvik: #SantRampalJiMaharaj_App\nMust know the reality about, who the Real God is, what is His name and how can we attain Him?\nGe\u2026"}, {"author_id": 1264376700776972288, "id": 1495251447214227462, "text": "RT @heartfeltbot: you realize, at last, that you can change without disappearing, that all you had to do was wait until the storm passes yo\u2026"}, {"author_id": 1446067455693033472, "id": 1495251446778019842, "text": "RT @evermorebot: and when i got into the accident, the sight that flashed before me was your face, but when i walked up to the podium i thi\u2026"}, {"author_id": 1433576067701227550, "id": 1495251446010286080, "text": "the \u00a0 blood \u00a0 of \u00a0 the \u00a0 goddess \u00a0 you \u00a0 carry \u00a0 in \u00a0 your \u00a0 veins\u00a0 \ufe50 \u00a0 the \u00a0 prophecy \u00a0 deemed \u00a0 by \u00a0 the \u00a0 gods \u00a0 above \u00a0 you \u00a0 carry \u00a0 in \u00a0 your \u00a0 name\u00a0 ."}, {"author_id": 3194935543, "id": 1495251438024470528, "text": "@kzzrttt Your account has exposed me to the salty side of the vocaloid fandom, like adding -p to the name of your YT channel really is not that big of a deal. \ud83e\udd28"}, {"author_id": 2803688575, "id": 1495251437193883648, "text": "@JimTothSports @Jasonl8487 Exactly my point. You only ever point out 1 side. Horses stampeding into a peaceful protest is perfectly fine. But name calling is a problem. Your willfully blind. History will stand against what Trudeau stood for. People are feed up. If anything they have shown great restraint!"}, {"author_id": 1275981208065839105, "id": 1495251430839664640, "text": "@IWASTHELYGHT No. Just pointing out YOU didn\u2019t have valid points to support YOUR own thoughts so you changed the topic. If you can\u2019t handle debates w/o staying on topic  AND/OR resort to name calling, YOU have NO valid points. Now go to plan B &amp; block me. Otherwise support YOUR point!"}, {"author_id": 1245316442926362627, "id": 1495251429476290561, "text": "RT @yedam_kr: 220219\n\ud83d\udc64: ah sorry~ i forgot your name\n\ud83e\udd8a: oh im BANG YEDAM\n\ud83d\udc64: no~ no~ can i call you mine?\n\ud83e\udd8a: *shocked* oh yeahh *laughs*\n\nHE\u2026"}, {"author_id": 1409533032839712773, "id": 1495251422224719872, "text": "RT @SagarRithvik: #SantRampalJiMaharaj_App\nMust know the reality about, who the Real God is, what is His name and how can we attain Him?\nGe\u2026"}, {"author_id": 1467978924990902273, "id": 1495251419942854656, "text": "Oh, you wanna \nspread toxicity and lies\nand then bring up my name? \nFuck you &amp; your shitty family."}, {"author_id": 1437086412361191425, "id": 1495251419242250243, "text": "RT @yedam_kr: 220219\n\ud83d\udc64: ah sorry~ i forgot your name\n\ud83e\udd8a: oh im BANG YEDAM\n\ud83d\udc64: no~ no~ can i call you mine?\n\ud83e\udd8a: *shocked* oh yeahh *laughs*\n\nHE\u2026"}, {"author_id": 1254989210148376577, "id": 1495251417065533443, "text": "RT @DaRealCanibus: \ud83d\udde3This SUNDAY is the LAST DAY  to PRE-ORDER  your copy of \"The Almighty Era\" V.1 2xCD w/ 34 Tracks and have your name fea\u2026"}, {"author_id": 1485565838107508741, "id": 1495251411180814343, "text": "RT @maycenturyormay: @iAmVJAndy Awww, Undi is still trying to make money out of @itsmetejasswi \u2018s name. Anyway, Undi, get a new job, bro. ;\u2026"}, {"author_id": 1014710092334227457, "id": 1495251410274820104, "text": "RT @KateMillerGems: \ud83d\udcb8 I will invest for sure!!\n\n\ud83d\udea8 PancakeSwap x @cloudnamecom \ud83d\udea8\n\n\ud83d\udc49Date: 22th February at 17 UTC\n\ud83d\udc49Token Name : $CNAME\n\ud83d\udc49Total\u2026"}, {"author_id": 1385095642318508032, "id": 1495251399348731906, "text": "RT @GeorgePapa19: It didn\u2019t take long to go from wash your hands to freezing bank accounts. All in the name of \u201cpublic health.\u201d"}, {"author_id": 728466331146682370, "id": 1495251396253208579, "text": "@ethoz @ethos You could change your name to ethoz if you don't get it back."}, {"author_id": 1444627756449341448, "id": 1495251395808796676, "text": "RT @ExoTerraNFTs: \u2692\ufe0f\ud83d\udd2530 #ExoCompetents Spots Giveaway\ud83d\udd25\u2692\ufe0f\n\n'Ice and iron can be welded.'\n\n\ud83d\udcac Name of this #ExoForge\n\u2764\ufe0f &amp; \ud83d\udd01\n\nTop 10 Names -&gt; G\u2026"}, {"author_id": 963618197323862018, "id": 1495251383859044352, "text": "@DelhiJalBoard @uditprakash For redressal of your complaint could you please help us with the following\nNAME: p p mehata\nADDRESS:136,B gulabi bagh\nCONTACT NO.: 9311155449\nKNO: 1827601000\nZone: cz2 / Prasad nagar\nIssue: we are not getting bills, please reverse late fees has not been adjusted 176.81 and 40.48"}, {"author_id": 399450800, "id": 1495251359498706946, "text": "I\u2019ll get your name next time and datix you. Bwesit"}, {"author_id": 1490878922036158467, "id": 1495251356390543360, "text": "@Kornweed666 @Pogrigand @yndranth You do understand when you \"Ship\" somebody you like the idea of both the people being in the same relationship right? Plus the fact that you are trying to pass this off as \"Not sexual\" When you clearly have hearts around \"Sonails\" in your name LMFAO"}, {"author_id": 446620107, "id": 1495251355581169664, "text": "cause my heart breaks a little when I hear your name"}, {"author_id": 855672628748668928, "id": 1495251348920614913, "text": "RT @muthoni_njakwe: God,\nThank you for this beautiful Sunday. Thank You for promising to be with us always, and for being the same yesterda\u2026"}, {"author_id": 1339974556748972035, "id": 1495251338128609280, "text": "RT @ProphetJoLynne: \ud83d\udca5Your enemies better enjoy their moment while they think they\u2019re winning! Because it\u2019s all about to come crashing down,\u2026"}, {"author_id": 706123096806330368, "id": 1495251331094913029, "text": "RT @julie_dutto: URGENT: A rebel group kidnapped a pangolin and demanded a ransom. Add your name NOW to protect Africa's pangolins and shut\u2026"}, {"author_id": 1319482448, "id": 1495251327785762816, "text": "Show your proof; Proof that whatever else you may forget, you will remain yourself, now, simply call my name #EleganceBot"}, {"author_id": 1428003443097079816, "id": 1495251326447538176, "text": "RT @hashmons: Let's drop another teaser reveal shall we! Can you guess this Hashmon's name? \ud83d\udc40\n\nHint: It's a \ud83d\udd25 type\n\nLike, Retweet and Tag y\u2026"}, {"author_id": 1337981253425905666, "id": 1495251315257069569, "text": "reply with your name and i'll rate how moanable it is under my breath"}, {"author_id": 4823070971, "id": 1495251313168470020, "text": "RT @Pastor__West: Dear Lord,\n\nToday, thank You for the gift of a new day. You promised in Your word that if I ask anything according to You\u2026"}, {"author_id": 1398251583415095297, "id": 1495251312992481287, "text": "RT @Nathuram_patel1: Must know the reality about, who the Real God is, what is His name and how can we attain Him?\nGet all your answers in\u2026"}, {"author_id": 4505110601, "id": 1495251312132427777, "text": "@adamcarolla Lia also swept up two other Gold Medals this weekend, for Women's 200M Pissing Your Name in the Snow, and for the Women's Freestyle Leaving the Toilet Seat Up."}, {"author_id": 1314784381676945409, "id": 1495251311478071296, "text": "RT @IndigoEternal: \ud83d\udcab FREE CAREER GUIDANCE \ud83d\udcab\nOne card tarot pull for general career advice. Must be following, RT, and react to this post. P\u2026"}, {"author_id": 1406773730278313986, "id": 1495251307497672706, "text": "RT @IncRelapse: A lot of my patients come to very shy timid afraid and in denial but that\u2019s how I like them because eventually all they wou\u2026"}, {"author_id": 765206620683010048, "id": 1495251305618501632, "text": "RT @DrAnjaliTai: Today and rest of the days of the year also it\u2019s only RAJE in the air.\nYour body goes into shivers while giving slogans of\u2026"}, {"author_id": 703052849039675393, "id": 1495251300887449601, "text": "Sags (is that how you spell it?) are the Shakes. No one calls them by their full name, they are very romantic to your face but secretly absolute snakes who will most often disappoint you romantically. But very good friends"}, {"author_id": 1376079093574160392, "id": 1495251300829007875, "text": "RT @yedam_kr: 220219\n\ud83d\udc64: ah sorry~ i forgot your name\n\ud83e\udd8a: oh im BANG YEDAM\n\ud83d\udc64: no~ no~ can i call you mine?\n\ud83e\udd8a: *shocked* oh yeahh *laughs*\n\nHE\u2026"}, {"author_id": 545239523, "id": 1495251295946612736, "text": "@Milrandor @Sledgefor17 @Titans That was with quite a bit of disrespect.  Good to see bribery, coercion and name calling are your preferred methods to achieve results.  I completely understand how our city, state and Federal Government wastes billions of dollars annually on this quid pro quo arrangement."}, {"author_id": 21298005, "id": 1495251290770739204, "text": "#NowPlaying Your NAme by Rhonda Glanton on #WNIAGospelRadio #cmesoar2 #ListenLive | WE ARE ON THE TUNEIN APP!"}, {"author_id": 39865773, "id": 1495251288455622659, "text": "Before you coach HS, perhaps you could put your name in the hat for the Texans head coaching job post Lovie. https://t.co/ZKCqcwdaEq"}, {"author_id": 1484044871769985025, "id": 1495251282168270850, "text": "@TheRickyDavila @AOC typical name calling lib without a point to make and missing the intellect to do so.......why do you even bother tweeting your racist pap?"}, {"author_id": 20969819, "id": 1495251282004750346, "text": "@Moviegirl773 @TrishAnderson32 @AggreyOrlea @Suzyqfit4u @DonnaLeigh5557 P.S. I used quotes, because I assumed your name is actually \"Moviegirl,\" so..."}, {"author_id": 1212095539572985856, "id": 1495251281929129987, "text": "RT @HWarlow: Oooh the red plush sofa is meant for sitting with a cuppa and having a natter with a friend , or with your nose in a book(me)\u2026"}, {"author_id": 1429225702952480781, "id": 1495251275096723458, "text": "RT @HermelaTV: Here's one easy way to take action &amp; say #nomore to #HR6600, a reckless bill that will only prolong the suffering of all peo\u2026"}, {"author_id": 885335746663636992, "id": 1495251266469085194, "text": "u ever have one of those days at work where its so busy and feels neverending and suddenly living off the grid under a boulder in the appalachian mountains with a single leaf to your name sounds better than being a functioning member of society"}, {"author_id": 236328848, "id": 1495251263386447873, "text": "@MichaelWestBiz Thanks for your support but correction needed. Frydenberg's name was on the list in  2017-8 and Ray Hadley \u0192irst called for gov to do a proper audit on basis of document showing family arrived in Australia on valid passport https://t.co/9Aa7udpYv1"}, {"author_id": 1243554643441057794, "id": 1495251258827210752, "text": "RT @rekhainsa72065: #SpiritualSunday If you want to lead a life of spiritual peace and peace, then remember the name of GOD,   He will bles\u2026"}, {"author_id": 1405201634263650304, "id": 1495251253747929089, "text": "RT @enzosalad: So my dad is a Ferdinand Marcos apologist but will not vote BBM. I asked why? And he said , \u201cparang ikaw- you made a name fo\u2026"}]